Metadata-Version: 2.1
Name: typer-router
Version: 1.1.0
Summary: Build Typer CLI Apps with File System-Based Routing
Home-page: https://github.com/nickderobertis/typer-router
Author: Nick DeRobertis
Author-email: derobertis.nick@gmail.com
License: MIT
Project-URL: Code, https://github.com/nickderobertis/typer-router
Project-URL: Documentation, https://nickderobertis.github.io/typer-router
Classifier: Development Status :: 3 - Alpha
Classifier: Intended Audience :: Developers
Classifier: Programming Language :: Python :: 3.6
Classifier: Programming Language :: Python :: 3.7
License-File: LICENSE.md
Requires-Dist: typer
Requires-Dist: pydantic
